dalimil/__init__.py
dalimil/actions.py
dalimil/dalimil.py
dalimil-2.0.1.dist-info/DESCRIPTION.rst
dalimil-2.0.1.dist-info/METADATA
dalimil-2.0.1.dist-info/RECORD
dalimil-2.0.1.dist-info/WHEEL
dalimil-2.0.1.dist-info/entry_points.txt
dalimil-2.0.1.dist-info/metadata.json
dalimil-2.0.1.dist-info/pbr.json
dalimil-2.0.1.dist-info/top_level.txt
