Metadata-Version: 2.0
Name: dalimil
Version: 2.0.1
Summary: CLI to archive files into time related containers (directories or archives).
Home-page: https://bitbucket.org/vlcinsky/dalimil
Author: Jan Vlcinsky
Author-email: jan.vlcinsky@tamtamresearch.com
License: BSD
Keywords: archive
Requires-Dist: argparse; (python_version=='2.6')
